prereform2modern/__init__.py
prereform2modern/dict_settings.py
prereform2modern/meta_data.py
prereform2modern/preprocess.py
prereform2modern/process.py
prereform2modern/token_class.py
prereform2modern/tokenizer.py
prereform2modern/translit_from_string.py
prereform2modern/transliterator.py
prereform2modern/word_tokenize.py
prereform2modern/datasets/adjectives_ija_ends.csv
prereform2modern/datasets/all_prefixes.csv
prereform2modern/datasets/freq.csv
prereform2modern/datasets/ozhegov.csv
prereform2modern/datasets/perfect_verbs.csv
prereform2modern/datasets/sharov.csv
prereform2modern/datasets/soft_sign_ends.csv
prereform2modern/datasets/ushakov.csv
prereform2modern/datasets/zaliznyak.csv
tests/integration/__init__.py
tests/system/__init__.py
tests/system/test_process.py
tests/system/test_translit_from_string.py
tests/unit/__init__.py
tests/unit/test_process.py
tests/unit/test_word_tokenize.py
prereform2modern-1.0.0.dist-info/LICENSE.txt
prereform2modern-1.0.0.dist-info/METADATA
prereform2modern-1.0.0.dist-info/WHEEL
prereform2modern-1.0.0.dist-info/entry_points.txt
prereform2modern-1.0.0.dist-info/top_level.txt
prereform2modern-1.0.0.dist-info/RECORD
