Metadata-Version: 2.1
Name: prereform2modern
Version: 1.0.0
Summary: Pre-reform to contemporary orthography convertor for the Russian language
Home-page: https://github.com/dhhse/prereform2modern
Author: Elena Sidorova
Author-email: dskorinkin@hse.ru
License: MIT
Keywords: prereform contemporary orthography convertor Russian
Platform: UNKNOWN
Classifier: License :: OSI Approved :: MIT License
Classifier: Programming Language :: Python :: 3
Classifier: Programming Language :: Python :: 3.6
Requires-Python: >=3.6.0,<4.0.0
